{
    "appId": "6D6X6",
    "version": "2.5.11.0",
    "minimumVersion": "0.0.0.0",
    "downloadUrl": "https://github.com/Lawrik17/BotMTS/releases/download/ea-license-resolver-20260723/6D6X6-2.5.11.0.zip",
    "updaterUrl": "https://github.com/Lawrik17/BotMTS/releases/download/hardware-20260719/Updater.exe",
    "sha256": "6beef69839025419b0870f0e12d52fa212149f815cf156dd6cb6589d0711a1de",
    "releaseNotes": "6D6X6 2.5.11.0: EA-игры определяются одновременно по базе MTS UserGame.db, InstallData, путям и журналам EA; добавлено ожидание появления данных. Во время EA-сценария окна независимо запущенного Steam мягко сворачиваются и больше не перехватывают фокус. Полный пакет включает Apps, службу и helper-лаунчеры.",
    "files": []
}
